hmsysteme/__init__.py
hmsysteme/functions.py
hmsysteme-1.98.dist-info/METADATA
hmsysteme-1.98.dist-info/WHEEL
hmsysteme-1.98.dist-info/top_level.txt
hmsysteme-1.98.dist-info/RECORD
