Metadata-Version: 2.4
Name: hmsysteme
Version: 1.98
Summary: Connection to HM01
Home-page: https://github.com/simbabali/hmsysteme
Download-URL: https://github.com/simbabali/hmsysteme/archive/v0.2.tar.gz
Author: stan
Author-email: stan3@gmx.net
License: MIT
Requires-Dist: pygame
Requires-Dist: pymunk
Requires-Dist: remi
Requires-Dist: smbus2
Requires-Dist: pyserial
Requires-Dist: matplotlib
Requires-Dist: Shared-Memory-Dict
Requires-Dist: pyopengl
Requires-Dist: setuptools
Dynamic: author
Dynamic: author-email
Dynamic: download-url
Dynamic: home-page
Dynamic: license
Dynamic: requires-dist
Dynamic: summary
